simple_portfolio/__init__.py
simple_portfolio/calculate.py
simple_portfolio/cli.py
simple_portfolio/export.py
simple_portfolio/fetch.py
simple_portfolio/util.py
simple_portfolio-0.1.8.dist-info/METADATA
simple_portfolio-0.1.8.dist-info/RECORD
simple_portfolio-0.1.8.dist-info/WHEEL
simple_portfolio-0.1.8.dist-info/entry_points.txt
simple_portfolio-0.1.8.dist-info/top_level.txt
