Metadata-Version: 2.1
Name: simple-portfolio
Version: 0.1.8
Summary: Simple portfolio metrics for Robinhood
Home-page: https://github.com/westonplatter/simple_portfolio/
Author: Weston Platter
Author-email: westonplatter@gmail.com
License: UNKNOWN
Platform: UNKNOWN
Requires-Dist: click
Requires-Dist: fast-arrow (>=0.1.0)
Requires-Dist: pandas
Requires-Dist: numpy
